{
  "type": "Feature",
  "properties": {
    "gn:asciiname":"Citern Village",
    "gn:country_code":"GD",
    "gn:dem":28,
    "gn:feature_class":"P",
    "gn:feature_code":"PPL",
    "gn:name":"Citern Village",
    "gn:population":0,
    "gn:timezone":"America/Grenada",
    "iso:country":"GD",
    "wof:name":"Citern Village",
    "wof:placetype":"locality"
},
  "geometry": {"coordinates":[-61.39096,12.5178],"type":"Point"}
}