{
  "type": "Feature",
  "properties": {
    "gn:admin1_code":"03",
    "gn:asciiname":"Marian",
    "gn:country_code":"GD",
    "gn:dem":13,
    "gn:feature_class":"P",
    "gn:feature_code":"PPL",
    "gn:name":"Marian",
    "gn:population":0,
    "gn:timezone":"America/Grenada",
    "iso:country":"GD",
    "name:fas_x_preferred":[
        "\u0645\u0627\u0631\u06cc\u0627\u0646"
    ],
    "name:ita_x_preferred":[
        "Marian"
    ],
    "name:nld_x_preferred":[
        "Marian"
    ],
    "name:rus_x_preferred":[
        "\u041c\u0430\u0440\u044c\u044f\u043d"
    ],
    "wof:name":"Marian",
    "wof:placetype":"locality"
},
  "geometry": {"coordinates":[-61.71666999999999,12.01667],"type":"Point"}
}