{
  "type": "Feature",
  "properties": {
    "gn:admin1_code":"03",
    "gn:asciiname":"Marian",
    "gn:country_code":"GD",
    "gn:dem":13,
    "gn:feature_class":"P",
    "gn:feature_code":"PPL",
    "gn:name":"Marian",
    "gn:population":0,
    "gn:timezone":"America/Grenada",
    "iso:country":"GD",
    "wof:name":"Marian",
    "wof:placetype":"locality"
},
  "geometry": {"coordinates":[-61.71666999999999,12.01667],"type":"Point"}
}