{
  "type": "Feature",
  "properties": {
    "gn:admin1_code":"01",
    "gn:asciiname":"Pearls",
    "gn:country_code":"GD",
    "gn:dem":22,
    "gn:feature_class":"P",
    "gn:feature_code":"PPL",
    "gn:name":"Pearls",
    "gn:population":0,
    "gn:timezone":"America/Grenada",
    "iso:country":"GD",
    "wof:name":"Pearls",
    "wof:placetype":"locality"
},
  "geometry": {"coordinates":[-61.61666999999999,12.15],"type":"Point"}
}