{
  "type": "Feature",
  "properties": {
    "gn:admin1_code":"04",
    "gn:asciiname":"Concord",
    "gn:country_code":"GD",
    "gn:dem":164,
    "gn:feature_class":"P",
    "gn:feature_code":"PPL",
    "gn:name":"Concord",
    "gn:population":0,
    "gn:timezone":"America/Grenada",
    "iso:country":"GD",
    "wof:name":"Concord",
    "wof:placetype":"locality"
},
  "geometry": {"coordinates":[-61.73333,12.11667],"type":"Point"}
}