{
  "type": "Feature",
  "properties": {
    "gn:admin1_code":"04",
    "gn:asciiname":"Grand Roy",
    "gn:country_code":"GD",
    "gn:dem":21,
    "gn:feature_class":"P",
    "gn:feature_code":"PPL",
    "gn:name":"Grand Roy",
    "gn:population":0,
    "gn:timezone":"America/Grenada",
    "iso:country":"GD",
    "name:ceb_x_preferred":[
        "Grand Roy"
    ],
    "name:ell_x_preferred":[
        "\u0393\u03ba\u03c1\u03b1\u03bd\u03c4 \u03a1\u03bf\u03b0"
    ],
    "name:fas_x_preferred":[
        "\u06af\u0631\u0646\u062f \u0631\u0648\u06cc"
    ],
    "name:pol_x_preferred":[
        "Grand Roy"
    ],
    "name:swe_x_preferred":[
        "Grand Roy"
    ],
    "name:zho_x_preferred":[
        "\u5927\u7f85\u4f0a"
    ],
    "wof:name":"Grand Roy",
    "wof:placetype":"locality"
},
  "geometry": {"coordinates":[-61.74537,12.1322],"type":"Point"}
}