{
  "type": "Feature",
  "properties": {
    "gn:admin1_code":"02",
    "gn:asciiname":"The Park",
    "gn:country_code":"GD",
    "gn:dem":260,
    "gn:feature_class":"P",
    "gn:feature_code":"PPL",
    "gn:name":"The Park",
    "gn:population":0,
    "gn:timezone":"America/Grenada",
    "iso:country":"GD",
    "wof:name":"The Park",
    "wof:placetype":"locality"
},
  "geometry": {"coordinates":[-61.71666999999999,12.05],"type":"Point"}
}