{
  "type": "Feature",
  "properties": {
    "iso:country":"GD",
    "qs:gn_pop":0,
    "qs:name":"Westerhall Land Settlement",
    "qs:name_adm0":"Grenada",
    "qs:name_adm1":"Saint David",
    "qs:photos":354,
    "qs:photos_1k":72,
    "qs:photos_9k":2,
    "qs:photos_9r":5,
    "qs:photos_all":354,
    "qs:photos_sr":6,
    "qs:placetype":"Town",
    "qs:pop_sr":"0",
    "qs:woe_adm0":23424826,
    "wof:name":"Westerhall Land Settlement",
    "wof:placetype":"locality"
},
  "geometry": {"coordinates":[-61.727027,12.014838],"type":"Point"}
}