{
  "type": "Feature",
  "properties": {
    "gn:admin1_code":"05",
    "gn:asciiname":"Maran",
    "gn:country_code":"GD",
    "gn:dem":95,
    "gn:feature_class":"P",
    "gn:feature_code":"PPL",
    "gn:name":"Maran",
    "gn:population":0,
    "gn:timezone":"America/Grenada",
    "iso:country":"GD",
    "name:fra_x_preferred":[
        "Maran"
    ],
    "name:heb_x_preferred":[
        "\u05de\u05e8\u05df"
    ],
    "name:lad_x_preferred":[
        "Maran"
    ],
    "name:spa_x_preferred":[
        "Maran"
    ],
    "name:vie_x_preferred":[
        "Maran"
    ],
    "wof:name":"Maran",
    "wof:placetype":"locality"
},
  "geometry": {"coordinates":[-61.72198,12.17544],"type":"Point"}
}