{
  "type": "Feature",
  "properties": {
    "gn:admin1_code":"03",
    "gn:asciiname":"Boca",
    "gn:country_code":"GD",
    "gn:dem":300,
    "gn:feature_class":"P",
    "gn:feature_code":"PPL",
    "gn:name":"Boca",
    "gn:population":0,
    "gn:timezone":"America/Grenada",
    "iso:country":"GD",
    "name:ceb_x_preferred":[
        "Boca"
    ],
    "name:deu_x_preferred":[
        "Boca"
    ],
    "name:epo_x_preferred":[
        "Boca"
    ],
    "name:fra_x_preferred":[
        "Boca"
    ],
    "name:glg_x_preferred":[
        "Boca"
    ],
    "name:hun_x_preferred":[
        "Boca"
    ],
    "name:ita_x_preferred":[
        "Boca"
    ],
    "name:lmo_x_preferred":[
        "Boca"
    ],
    "name:nld_x_preferred":[
        "Boca"
    ],
    "name:por_x_preferred":[
        "Boca"
    ],
    "name:slk_x_preferred":[
        "Boca"
    ],
    "name:spa_x_preferred":[
        "Boca"
    ],
    "name:srp_x_preferred":[
        "\u0411\u043e\u0446\u0430"
    ],
    "name:swe_x_preferred":[
        "Boca"
    ],
    "name:ukr_x_preferred":[
        "\u0411\u043e\u043a\u0430"
    ],
    "wof:name":"Boca",
    "wof:placetype":"locality"
},
  "geometry": {"coordinates":[-61.71666999999999,12.06667],"type":"Point"}
}