{
  "type": "Feature",
  "properties": {
    "gn:admin1_code":"02",
    "gn:asciiname":"Terre Cannes",
    "gn:country_code":"GD",
    "gn:dem":343,
    "gn:feature_class":"P",
    "gn:feature_code":"PPL",
    "gn:name":"Terre Cannes",
    "gn:population":0,
    "gn:timezone":"America/Grenada",
    "iso:country":"GD",
    "wof:name":"Terre Cannes",
    "wof:placetype":"locality"
},
  "geometry": {"coordinates":[-61.66667,12.06667],"type":"Point"}
}