{
  "type": "Feature",
  "properties": {
    "gn:admin1_code":"01",
    "gn:asciiname":"Lower La Tante",
    "gn:country_code":"GD",
    "gn:dem":37,
    "gn:feature_class":"P",
    "gn:feature_code":"PPL",
    "gn:name":"Lower La Tante",
    "gn:population":0,
    "gn:timezone":"America/Grenada",
    "iso:country":"GD",
    "wof:name":"Lower La Tante",
    "wof:placetype":"locality"
},
  "geometry": {"coordinates":[-61.64643,12.05252],"type":"Point"}
}