{
  "type": "Feature",
  "properties": {
    "gn:admin1_code":"03",
    "gn:asciiname":"Cafe",
    "gn:country_code":"GD",
    "gn:dem":150,
    "gn:feature_class":"P",
    "gn:feature_code":"PPL",
    "gn:name":"Caf\u00e9",
    "gn:population":0,
    "gn:timezone":"America/Grenada",
    "iso:country":"GD",
    "wof:name":"Cafe",
    "wof:placetype":"locality"
},
  "geometry": {"coordinates":[-61.73333,12.03333],"type":"Point"}
}