{
  "type": "Feature",
  "properties": {
    "gn:admin1_code":"02",
    "gn:asciiname":"Belle Isle",
    "gn:country_code":"GD",
    "gn:dem":37,
    "gn:feature_class":"P",
    "gn:feature_code":"PPL",
    "gn:name":"Belle Isle",
    "gn:population":0,
    "gn:timezone":"America/Grenada",
    "iso:country":"GD",
    "wof:name":"Belle Isle",
    "wof:placetype":"locality"
},
  "geometry": {"coordinates":[-61.65075,12.03443],"type":"Point"}
}