{
  "type": "Feature",
  "properties": {
    "gn:admin1_code":"02",
    "gn:asciiname":"Belle Isle",
    "gn:country_code":"GD",
    "gn:dem":37,
    "gn:feature_class":"P",
    "gn:feature_code":"PPL",
    "gn:name":"Belle Isle",
    "gn:population":0,
    "gn:timezone":"America/Grenada",
    "iso:country":"GD",
    "name:ceb_x_preferred":[
        "Belle Isle"
    ],
    "name:deu_x_preferred":[
        "Belle Isle"
    ],
    "name:fra_x_preferred":[
        "Belle-\u00cele"
    ],
    "name:pol_x_preferred":[
        "Belle Isle"
    ],
    "name:rus_x_preferred":[
        "\u0411\u0435\u043b\u044c-\u0418\u043b\u044c"
    ],
    "name:swe_x_preferred":[
        "Belle Isle"
    ],
    "name:ukr_x_preferred":[
        "\u0411\u0435\u043b\u044c-\u0406\u043b\u044c"
    ],
    "wof:name":"Belle Isle",
    "wof:placetype":"locality"
},
  "geometry": {"coordinates":[-61.65075,12.03443],"type":"Point"}
}