{
  "type": "Feature",
  "properties": {
    "gn:admin1_code":"04",
    "gn:asciiname":"The Lance",
    "gn:country_code":"GD",
    "gn:dem":130,
    "gn:feature_class":"P",
    "gn:feature_code":"PPL",
    "gn:name":"The Lance",
    "gn:population":0,
    "gn:timezone":"America/Grenada",
    "iso:country":"GD",
    "wof:name":"The Lance",
    "wof:placetype":"locality"
},
  "geometry": {"coordinates":[-61.71666999999999,12.16667],"type":"Point"}
}