{
  "type": "Feature",
  "properties": {
    "gn:admin1_code":"01",
    "gn:asciiname":"Windsor",
    "gn:country_code":"GD",
    "gn:dem":237,
    "gn:feature_class":"P",
    "gn:feature_code":"PPLL",
    "gn:name":"Windsor",
    "gn:population":0,
    "gn:timezone":"America/Grenada",
    "iso:country":"GD",
    "wof:name":"Windsor",
    "wof:placetype":"locality"
},
  "geometry": {"coordinates":[-61.66838000000001,12.13246],"type":"Point"}
}