{
  "type": "Feature",
  "properties": {
    "gn:admin1_code":"03",
    "gn:asciiname":"Mount Moritz",
    "gn:country_code":"GD",
    "gn:dem":183,
    "gn:feature_class":"P",
    "gn:feature_code":"PPL",
    "gn:name":"Mount Moritz",
    "gn:population":0,
    "gn:timezone":"America/Grenada",
    "iso:country":"GD",
    "name:und_x_variant":[
        "Mount Morice",
        "Mount Marice",
        "Mont Moritz",
        "Mount Moritz"
    ],
    "wof:name":"Mount Moritz",
    "wof:placetype":"locality"
},
  "geometry": {"coordinates":[-61.74834,12.08236],"type":"Point"}
}