{
  "type": "Feature",
  "properties": {
    "gn:admin1_code":"03",
    "gn:asciiname":"Grand Mal",
    "gn:country_code":"GD",
    "gn:dem":126,
    "gn:feature_class":"P",
    "gn:feature_code":"PPL",
    "gn:name":"Grand Mal",
    "gn:population":0,
    "gn:timezone":"America/Grenada",
    "iso:country":"GD",
    "wof:name":"Grand Mal",
    "wof:placetype":"locality"
},
  "geometry": {"coordinates":[-61.75,12.06667],"type":"Point"}
}