{
  "type": "Feature",
  "properties": {
    "gn:admin1_code":"06",
    "gn:asciiname":"Trevellan",
    "gn:country_code":"GD",
    "gn:dem":44,
    "gn:feature_class":"P",
    "gn:feature_code":"PPL",
    "gn:name":"Trevellan",
    "gn:population":0,
    "gn:timezone":"America/Grenada",
    "iso:country":"GD",
    "wof:name":"Trevellan",
    "wof:placetype":"locality"
},
  "geometry": {"coordinates":[-61.63333000000001,12.21667],"type":"Point"}
}