{
  "type": "Feature",
  "properties": {
    "gn:admin1_code":"01",
    "gn:asciiname":"Pecher",
    "gn:country_code":"GD",
    "gn:dem":277,
    "gn:feature_class":"P",
    "gn:feature_code":"PPL",
    "gn:name":"P\u00eacher",
    "gn:population":0,
    "gn:timezone":"America/Grenada",
    "iso:country":"GD",
    "wof:name":"Pecher",
    "wof:placetype":"locality"
},
  "geometry": {"coordinates":[-61.68333000000001,12.11667],"type":"Point"}
}