{
  "type": "Feature",
  "properties": {
    "gn:admin1_code":"03",
    "gn:asciiname":"Beaulieu",
    "gn:country_code":"GD",
    "gn:dem":103,
    "gn:feature_class":"P",
    "gn:feature_code":"PPL",
    "gn:name":"Beaulieu",
    "gn:population":0,
    "gn:timezone":"America/Grenada",
    "iso:country":"GD",
    "name:bre_x_preferred":[
        "Beaulieu"
    ],
    "name:cat_x_preferred":[
        "Beaulieu"
    ],
    "name:ceb_x_preferred":[
        "Beaulieu"
    ],
    "name:deu_x_preferred":[
        "Beaulieu"
    ],
    "name:fra_x_preferred":[
        "Beaulieu"
    ],
    "name:ind_x_preferred":[
        "Beaulieu"
    ],
    "name:ita_x_preferred":[
        "Beaulieu"
    ],
    "name:jpn_x_preferred":[
        "\u30dc\u30fc\u30ea\u30e5\u30fc"
    ],
    "name:lmo_x_preferred":[
        "Beaulieu"
    ],
    "name:nds_x_preferred":[
        "Beaulieu"
    ],
    "name:nld_x_preferred":[
        "Beaulieu"
    ],
    "name:oci_x_preferred":[
        "Beaulieu"
    ],
    "name:pms_x_preferred":[
        "Beaulieu"
    ],
    "name:pol_x_preferred":[
        "Beaulieu"
    ],
    "name:por_x_preferred":[
        "Beaulieu"
    ],
    "name:ron_x_preferred":[
        "Beaulieu"
    ],
    "name:rus_x_preferred":[
        "\u0411\u043e\u043b\u044c\u0451"
    ],
    "name:sco_x_preferred":[
        "Beaulieu"
    ],
    "name:slk_x_preferred":[
        "Beaulieu"
    ],
    "name:spa_x_preferred":[
        "Beaulieu"
    ],
    "name:sqi_x_preferred":[
        "Beaulieu"
    ],
    "name:srp_x_preferred":[
        "\u0411\u043e\u043b\u0438\u0458\u0435"
    ],
    "name:swe_x_preferred":[
        "Beaulieu"
    ],
    "name:ukr_x_preferred":[
        "\u0411\u043e\u043b\u044c\u0454"
    ],
    "wof:name":"Beaulieu",
    "wof:placetype":"locality"
},
  "geometry": {"coordinates":[-61.73333,12.06667],"type":"Point"}
}