{
  "type": "Feature",
  "properties": {
    "gn:admin1_code":"03",
    "gn:asciiname":"Tempe",
    "gn:cc2":"GD",
    "gn:country_code":"GD",
    "gn:dem":90,
    "gn:feature_class":"P",
    "gn:feature_code":"PPL",
    "gn:name":"Tempe",
    "gn:population":0,
    "gn:timezone":"America/Grenada",
    "iso:country":"GD",
    "name:und_x_variant":[
        "Temple",
        "Tempe"
    ],
    "wof:name":"Tempe",
    "wof:placetype":"locality"
},
  "geometry": {"coordinates":[-61.73333,12.05],"type":"Point"}
}