{
  "type": "Feature",
  "properties": {
    "gn:admin1_code":"01",
    "gn:asciiname":"Hope Bacolet",
    "gn:country_code":"GD",
    "gn:dem":58,
    "gn:feature_class":"P",
    "gn:feature_code":"PPL",
    "gn:name":"Hope Bacolet",
    "gn:population":0,
    "gn:timezone":"America/Grenada",
    "iso:country":"GD",
    "wof:name":"Hope Bacolet",
    "wof:placetype":"locality"
},
  "geometry": {"coordinates":[-61.62238000000001,12.07883],"type":"Point"}
}