{
  "type": "Feature",
  "properties": {
    "gn:admin1_code":"00",
    "gn:asciiname":"L'Appelle",
    "gn:country_code":"GD",
    "gn:dem":16,
    "gn:feature_class":"P",
    "gn:feature_code":"PPL",
    "gn:name":"L\u2019Appelle",
    "gn:population":0,
    "gn:timezone":"America/Grenada",
    "iso:country":"GD",
    "wof:name":"L'Appelle",
    "wof:placetype":"locality"
},
  "geometry": {"coordinates":[-61.43346999999999,12.52272],"type":"Point"}
}