{
  "type": "Feature",
  "properties": {
    "gn:asciiname":"Magazine Beach",
    "gn:country_code":"GD",
    "gn:dem":19,
    "gn:feature_class":"P",
    "gn:feature_code":"PPL",
    "gn:name":"Magazine Beach",
    "gn:population":0,
    "gn:timezone":"America/Grenada",
    "iso:country":"GD",
    "wof:name":"Magazine Beach",
    "wof:placetype":"locality"
},
  "geometry": {"coordinates":[-61.78196,12.01239],"type":"Point"}
}